yakc.so
yakc-0.1.5.dist-info/DESCRIPTION.rst
yakc-0.1.5.dist-info/METADATA
yakc-0.1.5.dist-info/metadata.json
yakc-0.1.5.dist-info/RECORD
yakc-0.1.5.dist-info/top_level.txt
yakc-0.1.5.dist-info/WHEEL
