Metadata-Version: 2.0
Name: yakc
Version: 0.1.5
Summary: Yet Another Kyoto Cabinet Binding
Home-page: https://github.com/informationsea/Yet-Another-Kyoto-Cabinet-Python-Binding
Author: OKAMURA Yasunobu
Author-email: okamura@informationsea.info
License: GPL3
Platform: UNKNOWN
Classifier: Intended Audience :: Developers
Classifier: License :: OSI Approved :: GNU General Public License v3 or later (GPLv3+)
Classifier: Programming Language :: Python :: 2.7
